static_qualname/__init__.py
static_qualname/__main__.py
static_qualname/core.py
static_qualname-0.2.0.dist-info/LICENSE
static_qualname-0.2.0.dist-info/METADATA
static_qualname-0.2.0.dist-info/WHEEL
static_qualname-0.2.0.dist-info/top_level.txt
static_qualname-0.2.0.dist-info/RECORD
